odmfclient/__init__.py
odmfclient/apiclient.py
odmfclient-0.1.2.dist-info/LICENSE
odmfclient-0.1.2.dist-info/METADATA
odmfclient-0.1.2.dist-info/WHEEL
odmfclient-0.1.2.dist-info/top_level.txt
odmfclient-0.1.2.dist-info/RECORD
