Metadata-Version: 2.1
Name: odmfclient
Version: 0.1.2
Summary: A Python client for ODMF's REST-API
Author-email: Philipp Kraft <philipp.kraft@envr.jlug.de>
License: MIT License
Project-URL: Homepage, https://github.com/jlu-ilr-hydro/odmfclient
Project-URL: Bug Tracker, https://github.com/jlu-ilr-hydro/odmfclient/issues
Classifier: Programming Language :: Python :: 3
Classifier: License :: OSI Approved :: MIT License
Classifier: Operating System :: OS Independent
Requires-Python: >=3.9
License-File: LICENSE
Requires-Dist: pandas
Requires-Dist: requests
Requires-Dist: pyyaml
Requires-Dist: pyarrow
